{
	"configurations" : 
	[
		{
			"directories" : 
			[
				{
					"build" : ".",
					"jsonFile" : "directory-.-Debug-f5ebdc15457944623624.json",
					"minimumCMakeVersion" : 
					{
						"string" : "3.10"
					},
					"projectIndex" : 0,
					"source" : ".",
					"targetIndexes" : 
					[
						0,
						1,
						2,
						3,
						4
					]
				}
			],
			"name" : "Debug",
			"projects" : 
			[
				{
					"directoryIndexes" : 
					[
						0
					],
					"name" : "journal_app",
					"targetIndexes" : 
					[
						0,
						1,
						2,
						3,
						4
					]
				}
			],
			"targets" : 
			[
				{
					"directoryIndex" : 0,
					"id" : "journal_app::@6890427a1f51a3e7e1df",
					"jsonFile" : "target-journal_app-Debug-e87678f95b05100e3894.json",
					"name" : "journal_app",
					"projectIndex" : 0
				},
				{
					"directoryIndex" : 0,
					"id" : "journal_lib::@6890427a1f51a3e7e1df",
					"jsonFile" : "target-journal_lib-Debug-222cd5ae0024f13258ef.json",
					"name" : "journal_lib",
					"projectIndex" : 0
				},
				{
					"directoryIndex" : 0,
					"id" : "journal_tests::@6890427a1f51a3e7e1df",
					"jsonFile" : "target-journal_tests-Debug-feda0a42d0c62bd9db95.json",
					"name" : "journal_tests",
					"projectIndex" : 0
				},
				{
					"directoryIndex" : 0,
					"id" : "stats_collector::@6890427a1f51a3e7e1df",
					"jsonFile" : "target-stats_collector-Debug-4882ffe1e96b2b2ba10a.json",
					"name" : "stats_collector",
					"projectIndex" : 0
				},
				{
					"directoryIndex" : 0,
					"id" : "stats_tests::@6890427a1f51a3e7e1df",
					"jsonFile" : "target-stats_tests-Debug-4dc94ac9287e8b18adf2.json",
					"name" : "stats_tests",
					"projectIndex" : 0
				}
			]
		}
	],
	"kind" : "codemodel",
	"paths" : 
	{
		"build" : "/home/leviafan-desktop/Projects/messages-lib-app/build",
		"source" : "/home/leviafan-desktop/Projects/messages-lib-app"
	},
	"version" : 
	{
		"major" : 2,
		"minor" : 6
	}
}
